MANIFEST.in
README.rst
requirements.txt
setup.py
openslides_gui/__init__.py
openslides_gui/__main__.py
openslides_gui/gui.py
openslides_gui.egg-info/PKG-INFO
openslides_gui.egg-info/SOURCES.txt
openslides_gui.egg-info/dependency_links.txt
openslides_gui.egg-info/entry_points.txt
openslides_gui.egg-info/requires.txt
openslides_gui.egg-info/top_level.txt
openslides_gui/data/openslides-logo_wide.png
openslides_gui/data/openslides.ico