Metadata-Version: 1.1
Name: openslides-gui
Version: 1.1.3
Summary: GUI frontend for managing OpenSlides server
Home-page: https://github.com/OpenSlides/openslides-gui
Author: OpenSlides-Team, see README
Author-email: support@openslides.org
License: MIT
Keywords: OpenSlides
Platform: UNKNOWN
Classifier: Development Status :: 5 - Production/Stable
Classifier: Environment :: Plugins
Classifier: Environment :: Web Environment
Classifier: Framework :: Django
Classifier: License :: OSI Approved :: MIT License
Classifier: Operating System :: OS Independent
Classifier: Programming Language :: Python :: 3.4
Classifier: Programming Language :: Python :: 3.5
